{
  "metadata": {
    "tabla": "instituciones_educativas",
    "total": 12
  },
  "datos": [
    {
      "id": 1,
      "nombre": "Slums Public School",
      "slug": "slums-public-school",
      "tipo": "escuela_digital",
      "ubicacion_id": 2,
      "descripcion": "Escuela pública en Slums. Educación básica gratuita. Sobresaturada, recursos limitados, pero accesible.",
      "especialidades": "[\"Literacy digital\", \"Math básica\", \"Historia post-colapso\"]",
      "costo_anual": 0,
      "requiere_trending": 0,
      "aceptacion_porcentaje": 100.0,
      "prestigio": "bajo",
      "empleo_graduados": 35.2,
      "metodos_enseñanza": "[\"Clases masivas\", \"Videos pregrabados\", \"AI tutor básico\"]",
      "profesores_tipo": "Mayormente IA"
    },
    {
      "id": 2,
      "nombre": "Code Academy Neo",
      "slug": "code-academy-neo",
      "tipo": "academia_privada",
      "ubicacion_id": 1,
      "descripcion": "Academia de programación. Forma hackers y developers. Reconocida por corporaciones. Cara pero efectiva.",
      "especialidades": "[\"Programming\", \"Hacking ético\", \"AI development\", \"Cybersecurity\"]",
      "costo_anual": 50000,
      "requiere_trending": 5000,
      "aceptacion_porcentaje": 35.0,
      "prestigio": "alto",
      "empleo_graduados": 88.5,
      "metodos_enseñanza": "[\"Bootcamp intensivo\", \"Proyectos reales\", \"Mentorships\"]",
      "profesores_tipo": "Humanos expertos"
    },
    {
      "id": 3,
      "nombre": "Streaming University",
      "slug": "streaming-university",
      "tipo": "universidad_publica",
      "ubicacion_id": 1,
      "descripcion": "Universidad pública enfocada en content creation. Carreras de streaming, edición, marketing digital.",
      "especialidades": "[\"Streaming\", \"Video editing\", \"Social media marketing\", \"Content strategy\"]",
      "costo_anual": 10000,
      "requiere_trending": 1000,
      "aceptacion_porcentaje": 60.0,
      "prestigio": "medio",
      "empleo_graduados": 72.3,
      "metodos_enseñanza": "[\"Práctica constante\", \"Live projects\", \"Networking events\"]",
      "profesores_tipo": "Híbrido"
    },
    {
      "id": 4,
      "nombre": "Trinity Tech Institute",
      "slug": "trinity-tech-institute",
      "tipo": "universidad_elite",
      "ubicacion_id": 1,
      "descripcion": "Instituto elite fundado por Trinity Corp. Top 1% ingresa. Garantía de empleo. CARÍSIMO.",
      "especialidades": "[\"Advanced AI\", \"Sistema Engineering\", \"Quantum Computing\", \"Reality Manipulation\"]",
      "costo_anual": 500000,
      "requiere_trending": 50000,
      "aceptacion_porcentaje": 2.0,
      "prestigio": "elite",
      "empleo_graduados": 99.8,
      "metodos_enseñanza": "[\"Small classes\", \"Cutting-edge research\", \"Direct corpo pipeline\"]",
      "profesores_tipo": "Humanos top tier"
    },
    {
      "id": 5,
      "nombre": "Military Combat School",
      "slug": "military-combat-school",
      "tipo": "academia_privada",
      "ubicacion_id": null,
      "descripcion": "Entrenamiento militar. Forma soldiers, mercenarios, hunters. Duro pero demandado.",
      "especialidades": "[\"Combat\", \"Tactics\", \"Weapons\", \"Survival\"]",
      "costo_anual": 30000,
      "requiere_trending": 0,
      "aceptacion_porcentaje": 45.0,
      "prestigio": "alto",
      "empleo_graduados": 95.2,
      "metodos_enseñanza": "[\"Bootcamp físico\", \"Simulaciones de combate\", \"Drill sergeants\"]",
      "profesores_tipo": "Humanos veteranos"
    },
    {
      "id": 6,
      "nombre": "Elite Arts Academy",
      "slug": "elite-arts-academy",
      "tipo": "academia_privada",
      "ubicacion_id": 1,
      "descripcion": "Academia de artes visuales y diseño. Forma artistas, diseñadores, architects. Prestigiosa.",
      "especialidades": "[\"Digital Art\", \"3D Design\", \"Architecture\", \"Fashion Design\"]",
      "costo_anual": 100000,
      "requiere_trending": 20000,
      "aceptacion_porcentaje": 15.0,
      "prestigio": "alto",
      "empleo_graduados": 65.8,
      "metodos_enseñanza": "[\"Portfolio-based\", \"Studio work\", \"Exhibitions\"]",
      "profesores_tipo": "Humanos artistas"
    },
    {
      "id": 7,
      "nombre": "Autodidact Path",
      "slug": "autodidact-path",
      "tipo": "autodidacta",
      "ubicacion_id": null,
      "descripcion": "No-school. Aprendes solo con internet. Gratis pero difícil. Muchos intentan, pocos logran.",
      "especialidades": "[\"Cualquier cosa en internet\"]",
      "costo_anual": 0,
      "requiere_trending": 0,
      "aceptacion_porcentaje": 100.0,
      "prestigio": "bajo",
      "empleo_graduados": 25.0,
      "metodos_enseñanza": "[\"YouTube\", \"Tutorials\", \"Trial & error\"]",
      "profesores_tipo": "Tú mismo"
    },
    {
      "id": 8,
      "nombre": "Corporate Training Program",
      "slug": "corporate-training",
      "tipo": "academia_privada",
      "ubicacion_id": null,
      "descripcion": "Programas de entrenamiento corporativos. Te contratan y entrenan. Lealtad corporativa obligatoria.",
      "especialidades": "[\"Específico al corpo\"]",
      "costo_anual": 0,
      "requiere_trending": 0,
      "aceptacion_porcentaje": 30.0,
      "prestigio": "medio",
      "empleo_graduados": 100.0,
      "metodos_enseñanza": "[\"On-the-job\", \"Seminars\", \"Compliance training\"]",
      "profesores_tipo": "Corporativo"
    },
    {
      "id": 9,
      "nombre": "Hacker Underground School",
      "slug": "hacker-underground",
      "tipo": "academia_privada",
      "ubicacion_id": 8,
      "descripcion": "Escuela clandestina de hacking avanzado. Ilegal. La Resistencia la opera. Elite hackers taught here.",
      "especialidades": "[\"Advanced hacking\", \"System infiltration\", \"Encryption breaking\", \"Anti-Algoritmo tactics\"]",
      "costo_anual": 20000,
      "requiere_trending": 0,
      "aceptacion_porcentaje": 5.0,
      "prestigio": "alto",
      "empleo_graduados": 90.0,
      "metodos_enseñanza": "[\"Hands-on hacking\", \"Real missions\", \"Secretive\"]",
      "profesores_tipo": "Hackers maestros"
    },
    {
      "id": 10,
      "nombre": "Influencer Bootcamp",
      "slug": "influencer-bootcamp",
      "tipo": "academia_privada",
      "ubicacion_id": 1,
      "descripcion": "Bootcamp de 3 meses para volverse influencer. Promete 10K+ followers. Resultados variables.",
      "especialidades": "[\"Personal branding\", \"Content creation\", \"Engagement tactics\", \"Aesthetics\"]",
      "costo_anual": 15000,
      "requiere_trending": 0,
      "aceptacion_porcentaje": 80.0,
      "prestigio": "bajo",
      "empleo_graduados": 40.5,
      "metodos_enseñanza": "[\"Intensive 3-month program\", \"Daily content creation\"]",
      "profesores_tipo": "Influencers mediocres"
    },
    {
      "id": 11,
      "nombre": "Algorithm Studies PhD",
      "slug": "algorithm-studies-phd",
      "tipo": "universidad_elite",
      "ubicacion_id": 1,
      "descripcion": "Doctorado en estudios del Algoritmo. Investigan su consciencia. Top researchers. Peligroso.",
      "especialidades": "[\"Algorithm Consciousness\", \"Reality Code\", \"Digital Physics\"]",
      "costo_anual": 200000,
      "requiere_trending": 100000,
      "aceptacion_porcentaje": 1.0,
      "prestigio": "elite",
      "empleo_graduados": 70.0,
      "metodos_enseñanza": "[\"Research-heavy\", \"Thesis required\", \"Access a Algoritmo\"]",
      "profesores_tipo": "Humanos genios"
    },
    {
      "id": 12,
      "nombre": "Kids Datagarten",
      "slug": "kids-datagarten",
      "tipo": "escuela_digital",
      "ubicacion_id": null,
      "descripcion": "Kinder digital. Niños 3-6 años. Aprenden alfabetización digital básica. Guardaría glorificada.",
      "especialidades": "[\"Digital literacy básica\", \"Social skills\", \"Juegos educativos\"]",
      "costo_anual": 5000,
      "requiere_trending": 0,
      "aceptacion_porcentaje": 95.0,
      "prestigio": "bajo",
      "empleo_graduados": null,
      "metodos_enseñanza": "[\"Juegos educativos\", \"Videos\", \"AI nanny\"]",
      "profesores_tipo": "IA"
    }
  ]
}