{
  "id": 6,
  "volumen": 1,
  "numero": 6,
  "titulo": "La Casa del Hype",
  "slug": "v1-c6-la-casa-del-hype",
  "publicado": 0,
  "fecha_publicacion": null,
  "fecha_creacion": "2026-02-10 14:59:15",
  "contenido_markdown": null,
  "contenido_html": null,
  "excerpt": "Los 5 Streamers controlan Ciudad Neón desde su rascacielos. Rampage, Bella, Critico, Prank Lord y Guru. Cada uno más tóxico que el anterior.",
  "palabras": 4100,
  "minutos_lectura": 16,
  "icono": "🏢",
  "personajes_aparecen": null,
  "ubicaciones": [],
  "enemigos_aparecen": null,
  "items_mencionados": null,
  "conceptos_mencionados": null,
  "eventos_ocurren": null,
  "anterior_slug": null,
  "siguiente_slug": null,
  "requiere_capitulo": 5,
  "bloqueado": 0,
  "meta_description": null,
  "meta_keywords": null,
  "meta_og_image": null,
  "meta_author": "Trending Ghost Official",
  "meta_published_time": null,
  "views_totales": 0,
  "likes": 0,
  "compartidos": 0,
  "comentarios": 0,
  "created_at": "2026-02-10 14:59:15",
  "updated_at": "2026-02-10 14:59:15",
  "vol_titulo": "JUNGLA DE NEÓN",
  "vol_numero": 1,
  "personajes": [],
  "enemigos": [],
  "eventos": []
}