{
  "id": 17,
  "volumen": 2,
  "numero": 17,
  "titulo": "Entrenamiento del Lag",
  "slug": "v2-c17-entrenamiento-del-lag",
  "publicado": 0,
  "fecha_publicacion": null,
  "fecha_creacion": "2026-02-10 14:59:15",
  "contenido_markdown": null,
  "contenido_html": null,
  "excerpt": "Lag Eternal ve potencial en Bazure. Le enseña a \"dominar el lag\" en vez de resistirlo. Filosofía del ping.",
  "palabras": 4000,
  "minutos_lectura": 16,
  "icono": "🥋",
  "personajes_aparecen": null,
  "ubicaciones": [],
  "enemigos_aparecen": null,
  "items_mencionados": null,
  "conceptos_mencionados": null,
  "eventos_ocurren": null,
  "anterior_slug": null,
  "siguiente_slug": null,
  "requiere_capitulo": 16,
  "bloqueado": 0,
  "meta_description": null,
  "meta_keywords": null,
  "meta_og_image": null,
  "meta_author": "Trending Ghost Official",
  "meta_published_time": null,
  "views_totales": 0,
  "likes": 0,
  "compartidos": 0,
  "comentarios": 0,
  "created_at": "2026-02-10 14:59:15",
  "updated_at": "2026-02-10 14:59:15",
  "vol_titulo": "DESIERTO LAG",
  "vol_numero": 2,
  "personajes": [],
  "enemigos": [],
  "eventos": []
}